daspi-1.8.0.dist-info/METADATA
daspi-1.8.0.dist-info/WHEEL
daspi-1.8.0.dist-info/entry_points.txt
daspi-1.8.0.dist-info/licenses/LICENSE
daspi/__init__.py
daspi/_typing.py
daspi/_version.py
daspi/anova/__init__.py
daspi/anova/convert.py
daspi/anova/model.py
daspi/anova/tables.py
daspi/constants.py
daspi/datasets/__init__.py
daspi/datasets/ancova.csv
daspi/datasets/anova.csv
daspi/datasets/anova2.csv
daspi/datasets/anova2_unbalanced.csv
daspi/datasets/anova3.csv
daspi/datasets/anova3_unbalanced.csv
daspi/datasets/carpet_full-factorial.csv
daspi/datasets/covariate.csv
daspi/datasets/drop_card.csv
daspi/datasets/eeprom_full-factorial.csv
daspi/datasets/eeprom_partial-factorial.csv
daspi/datasets/grnr_adjustment.csv
daspi/datasets/grnr_layer_thickness.csv
daspi/datasets/grnr_spc.csv
daspi/datasets/iris.csv
daspi/datasets/mpg.csv
daspi/datasets/painkillers-dissolution.csv
daspi/datasets/partial_factorial.csv
daspi/datasets/process_capability.mpx
daspi/datasets/salt_sticks.csv
daspi/datasets/shoe-sole.csv
daspi/datasets/tips.csv
daspi/doe/__init__.py
daspi/doe/build.py
daspi/plotlib/__init__.py
daspi/plotlib/appearance.py
daspi/plotlib/chart.py
daspi/plotlib/classify.py
daspi/plotlib/facets.py
daspi/plotlib/plotter.py
daspi/plotlib/precast.py
daspi/plotlib/styles/daspi-dark.mplstyle
daspi/plotlib/styles/daspi.mplstyle
daspi/plotlib/styles/ggplot2.mplstyle
daspi/plotlib/styles/seaborn.mplstyle
daspi/requirements.txt
daspi/statistics/__init__.py
daspi/statistics/confidence.py
daspi/statistics/estimation.py
daspi/statistics/hypothesis.py
daspi/statistics/montecarlo.py
daspi/strings.py
daspi-1.8.0.dist-info/RECORD
