Metadata-Version: 2.1
Name: DaSPi
Version: 1.8.0
Summary: Visualize and analyze your data with DaSPi. This package is designed for users who want to find relevant influencing factors in processes and validate improvements.
Author-Email: =?utf-8?q?Reto_J=C3=A4ggli?= <reto@jaeggli.email>
License: BSD-3-Clause
Project-URL: Repository, https://github.com/j4ggr/DaSPi
Project-URL: Documentation, https://j4ggr.github.io/DaSPi/
Project-URL: Changelog, https://j4ggr.github.io/DaSPi/Changelog
Requires-Python: >=3.11
Requires-Dist: matplotlib>=3.10.0
Requires-Dist: pandas>=2.1.4
Requires-Dist: statsmodels>=0.14.1
Requires-Dist: scipy>=1.11.4
Requires-Dist: numpy>=1.26.3
